velithon-0.6.10.dist-info/METADATA
velithon-0.6.10.dist-info/WHEEL
velithon-0.6.10.dist-info/entry_points.txt
velithon-0.6.10.dist-info/licenses/LICENSE
velithon.libs/libgcc_s-27e5a392.so.1
velithon/__init__.py
velithon/__main__.py
velithon/_utils.py
velithon/_velithon.cpython-312-i386-linux-musl.so
velithon/_velithon.pyi
velithon/application.py
velithon/background.py
velithon/base_datastructures.py
velithon/cli.py
velithon/convertors.py
velithon/ctx.py
velithon/datastructures.py
velithon/di.py
velithon/documentation.py
velithon/endpoint.py
velithon/event.py
velithon/exceptions/__init__.py
velithon/exceptions/base.py
velithon/exceptions/errors.py
velithon/exceptions/formatters.py
velithon/exceptions/http.py
velithon/gateway.py
velithon/logging.py
velithon/middleware/__init__.py
velithon/middleware/auth.py
velithon/middleware/base.py
velithon/middleware/compression.py
velithon/middleware/context.py
velithon/middleware/cors.py
velithon/middleware/logging.py
velithon/middleware/prometheus.py
velithon/middleware/proxy.py
velithon/middleware/session.py
velithon/openapi/__init__.py
velithon/openapi/constants.py
velithon/openapi/docs.py
velithon/openapi/ui.py
velithon/params/__init__.py
velithon/params/dispatcher.py
velithon/params/params.py
velithon/params/parser.py
velithon/py.typed
velithon/requests.py
velithon/responses/__init__.py
velithon/responses/base.py
velithon/responses/file.py
velithon/responses/html.py
velithon/responses/json.py
velithon/responses/plain_text.py
velithon/responses/proxy.py
velithon/responses/redirect.py
velithon/responses/sse.py
velithon/responses/streaming.py
velithon/routing.py
velithon/security/__init__.py
velithon/security/auth.py
velithon/security/dependencies.py
velithon/security/exceptions.py
velithon/security/jwt.py
velithon/security/models.py
velithon/security/permissions.py
velithon/security/utils.py
velithon/serialization.py
velithon/status.py
velithon/templates/__init__.py
velithon/templates/engine.py
velithon/websocket/__init__.py
velithon/websocket/channel.py
velithon/websocket/connection.py
velithon/websocket/endpoint.py
velithon/websocket/heartbeat.py
velithon/websocket/room.py
velithon-0.6.10.dist-info/RECORD
