Metadata-Version: 2.4
Name: velithon
Version: 0.6.10
Classifier: Development Status :: 4 - Beta
Classifier: Intended Audience :: Developers
Classifier: License :: OSI Approved :: BSD License
Classifier: Operating System :: OS Independent
Classifier: Programming Language :: Python :: 3
Classifier: Programming Language :: Python :: 3.10
Classifier: Programming Language :: Python :: 3.11
Classifier: Programming Language :: Python :: 3.12
Classifier: Programming Language :: Python :: 3.13
Classifier: Programming Language :: Python :: Implementation :: CPython
Classifier: Programming Language :: Rust
Classifier: Topic :: Internet :: WWW/HTTP :: HTTP Servers
Classifier: Topic :: Internet :: WWW/HTTP :: WSGI :: Server
Classifier: Topic :: Internet :: WWW/HTTP :: Dynamic Content
Classifier: Topic :: Software Development :: Libraries :: Application Frameworks
Classifier: Topic :: Software Development :: Libraries :: Python Modules
Classifier: Framework :: AsyncIO
Classifier: Environment :: Web Environment
Classifier: Typing :: Typed
Requires-Dist: granian[asyncio,reload,rloop,uvloop]>=2.2.6,<3.0.0
Requires-Dist: orjson>=3.10.16,<4.0.0
Requires-Dist: pydantic[email]>=2.11.7,<3.0.0
Requires-Dist: pyferris>=0.5.0,<1.0.0
Requires-Dist: markdown>=3.6,<4.0.0 ; extra == 'docs'
Requires-Dist: weasyprint>=66.0 ; extra == 'docs'
Requires-Dist: jinja2>=3.1.0,<4.0.0 ; extra == 'docs'
Provides-Extra: docs
License-File: LICENSE
Summary: Velithon is a lightweight, high-performance, asynchronous web framework for Python, built on top of the RSGI protocol
Author-email: Dang Van Nghiem <vannghiem848@gmail.com>
License: BSD-3-Clause
Requires-Python: >=3.10
